ifsc_expand/__init__.py
ifsc_expand/__main__.py
ifsc_expand/utils.py
ifsc_expand-1.0.0.dist-info/LICENSE
ifsc_expand-1.0.0.dist-info/METADATA
ifsc_expand-1.0.0.dist-info/WHEEL
ifsc_expand-1.0.0.dist-info/entry_points.txt
ifsc_expand-1.0.0.dist-info/top_level.txt
ifsc_expand-1.0.0.dist-info/RECORD
